[
  {
    "employer_name": "Cleaveland Clinic",
    "job_title": "RN - Emergency Department (ED)",
    "job_city": "Cleveland Clinic Main Campus",
    "job_state": "",
    "job_posted_at": "1d",
    "job_description": "• RN - Emergency Department (ED)locationsCleveland Clinic Main Campustime typePart timeposted onPosted Today298744RN - Emergency Department (ED)locationsCleveland Clinic Main Campustime typeFull timeposted onPosted Today292756Patient Service SpecialistlocationsCleveland Clinic Main Campustime typeFull timeposted onPosted Today318742RN - Med/Surg & OncologylocationsMercy Hospitaltime typeFull timeposted onPosted Today318663Environmental Services Area CleanerlocationsMarymount Hospitaltime typeFull timeposted onPosted Today319156RN - Emergency DepartmentlocationsAvon Hospitaltime typePart timeposted onPosted Today318515Mammography TechnologistlocationsAkron General Medical Centertime typeFull timeposted onPosted Today304897Mammography TechnologistlocationsAkron General Medical Centertime typePart timeposted onPosted Today259053Radiology Imaging AssociatelocationsAkron General Medical Centertime typeFull timeposted onPosted Today316044Environmental Services Area CleanerlocationsAvon Hospitaltime typeFull timeposted onPosted Today316959Patient Care Nursing Assistant – GYN Oncology Surgery/General SurgerylocationsHillcrest Hospitaltime typeFull timeposted onPosted Today315405Patient Care Nursing Assistant – Medical/SurgicallocationsHillcrest Hospitaltime typeFull timeposted onPosted Today317435Patient CompanionlocationsIndian River Hospitaltime typePart timeposted onPosted Today316018RN BU - Outpatient EndoscopylocationsIndian River Hospitaltime typeFull timeposted onPosted Today317898Patient CompanionlocationsIndian River Hospitaltime typeFull timeposted onPosted Yesterday315247Phlebotomy TechnicianlocationsMedina Hospitaltime typeFull timeposted onPosted Yesterday318578LPN Ambulatory - Family MedicinelocationsStow Falls Medical Office Centertime typeFull timeposted onPosted Yesterday314564RN Ambulatory - Outpatient InfusionlocationsMercy Hospitaltime typeFull timeposted onPosted Yesterday315762Medical Assistant- Adult Pulmonary/Peds SpecialtieslocationsStow Falls Medical Office Centertime typeFull timeposted onPosted Yesterday305092LPN Ambulatory REI/IVF - BeachwoodlocationsBeachwood Family Health and Surgery Centertime typeFull timeposted onPosted Yesterday305881.",
    "job_apply_link": "https://ccf.wd1.myworkdayjobs.com/en-US/ClevelandClinicCareers/job/Cleveland-Clinic-Main-Campus/RN---Emergency-Department--ED-_298744",
    "id": "cleaveland-clinic-rn-emergency-department-ed-cleveland-clinic-main-campus"
  }
]