[
  {
    "employer_name": "Cleaveland Clinic",
    "job_title": "Nurse Technician – Clinical Decision Unit",
    "job_city": "Akron General Medical Center",
    "job_state": "",
    "job_posted_at": "1d",
    "job_description": "• Nurse Technician – Clinical Decision UnitlocationsAkron General Medical Centertime typePart timeposted onPosted Today312823RN BU - Medical Diabetes and Med/SurglocationsIndian River Hospitaltime typeFull timeposted onPosted Today314848RN HOPS NE - ImaginglocationsCleveland Clinic Main Campustime typeFull timeposted onPosted Today317064Utilization Management SpecialistlocationsRemote Locationtime typePart timeposted onPosted Today294936RN - Internal Medicine UnitlocationsCleveland Clinic Main Campustime typeFull timeposted onPosted Today312746Advanced Practice Provider (ENP/PA) – Emergency Medicine III NIGHTS - Sign-on Bonus Eligible.\n• LocationsMarymount Hospitaltime typeFull timeposted onPosted Today292769Advanced Practice Provider (ENP/PA) – Emergency Medicine III - Sign-on Bonus Eligible.\n• LocationsMercy Hospitaltime typeFull timeposted onPosted Today268455LPN Ambulatory - Coumadin CliniclocationsLakewood Family Health Centertime typeFull timeposted onPosted Today310767Patient Care Nursing Assistant (PCNA) - Rapid Observation UnitlocationsAvon Hospitaltime typePart timeposted onPosted Today315209New Grad RN — Internal MedicinelocationsCleveland Clinic Main Campustime typePart timeposted onPosted Today255490RN Ambulatory Team Lead - Internal MedicinelocationsCleveland Clinic Main Campustime typeFull timeposted onPosted Today317141Surgical Technologist – Ambulatory Surgery Centerlocations2 Locationstime typeFull timeposted onPosted Today315469RN Ambulatory - OBGYNlocationsFairview Hospitaltime typePart timeposted onPosted Today316163Patient Care Nursing Assistant - Pediatric Intermediate Care Unit (ICU)locationsCleveland Clinic Main Campustime typePart timeposted onPosted Today317731Health Unit Coordinator – Neuroscience UnitlocationsMarymount Hospitaltime typeFull timeposted onPosted Today313100Patient Care Nursing Assistant - Intermediate Cardiac CarelocationsIndian River Hospitaltime typeFull timeposted onPosted Today314628Patient Access RepresentativelocationsLutheran Hospitaltime typePart timeposted onPosted Today313869Contact Center Support Operator IIlocationsFairview Hospitaltime typePart timeposted onPosted Today317883Contact Center Support Operator IIlocationsFairview Hospitaltime typePart timeposted onPosted Today317885Material Handler - Linen and LaundrylocationsMercy Hospitaltime typeFull timeposted onPosted Today314922.",
    "job_apply_link": "https://ccf.wd1.myworkdayjobs.com/en-US/ClevelandClinicCareers/job/Akron-General-Medical-Center/Nurse-Technician---Clinical-Decision-Unit_312823?q=nursing",
    "id": "cleaveland-clinic-nurse-technician-clinical-decision-unit-akron-general-medical-center"
  }
]